[
    {
        "Title": "­ЪњЦSI├іU PHр║еM 16Tр╗Х Mр║ХT PHр╗љ KIM M├Ѓ,BA ─љ├їNH-KINH DOANH ─љр╗ѕNH-Vр╗ѕA H├ѕ ─љ├Ђ B├ЊNG­ЪњЦ",
        "Description": "3 PN Рђб Nh├а mр║иt phр╗Љ, mр║иt tiр╗Ђn",
        "Price": "16 tр╗и",
        "Price per m┬▓": "457 tr/m┬▓",
        "Space": "35 m┬▓",
        "Location": "Quр║Гn Ba ─љ├гnh Рђб 3 ng├аy trк░р╗Џc"
    },
    {
        "Title": "CHр╗ѕ 3 Tр╗Х700TR NHр║гN NGAY C─ѓN 3PN2VS 80m FULL ─љр╗њ ─љр║ИP VIEW BIр╗ѓN Hр╗њ VHOCP",
        "Description": "3 PN Рђб Chung cк░",
        "Price": "16 tр╗и",
        "Price per m┬▓": "457 tr/m┬▓",
        "Space": "35 m┬▓",
        "Location": "Huyр╗Єn Gia L├бm Рђб 3 ng├аy trк░р╗Џc"
    },
    {
        "Title": "NHр╗ѕNH 2 Tр╗Х Tр║гP THр╗ѓ NGUYр╗ёN TR├ЃI DUPLEX 2 Tр║дNG 3 NGр╗д 80m2 2 WC nh├а ─Љр║╣p",
        "Description": "3 PN Рђб Tр║Гp thр╗Ѓ, cк░ x├А",
        "Price": "16 tр╗и",
        "Price per m┬▓": "457 tr/m┬▓",
        "Space": "35 m┬▓",
        "Location": "Quр║Гn Thanh Xu├бn Рђб 3 ng├аy trк░р╗Џc"
    },
    {
        "Title": "B├Аn nh├а 4 tр║Дng , ng├х 622 phр╗Љ Minh khai, gр║Дn Times City",
        "Description": "4 PN Рђб Hк░р╗Џng Bр║»c Рђб Nh├а ng├х, hр║╗m",
        "Price": "16 tр╗и",
        "Price per m┬▓": "457 tr/m┬▓",
        "Space": "35 m┬▓",
        "Location": "Quр║Гn Hai B├а Trк░ng Рђб 3 ng├аy trк░р╗Џc"
    },
    {
        "Title": "B├Аn 84m ─Љр║Цt gр║Дn ngay ─Љк░р╗Юng dр║Фn cр║Дu Tр╗Е Li├фn, Xu├бn Canh ─љ├┤ng Anh 12,xxty",
        "Description": "─љр║Цt thр╗Ћ cк░ Рђб Ngang 7 m",
        "Price": "16 tр╗и",
        "Price per m┬▓": "457 tr/m┬▓",
        "Space": "35 m┬▓",
        "Location": "Huyр╗Єn ─љ├┤ng Anh Рђб 3 ng├аy trк░р╗Џc"
    },
    {
        "Title": "NH├ђ ─љр║аI LA- SAU 1 NH├ђ RA PHр╗љ- 28M- CHр╗ѕ 5,38 Tр╗Х- NH├ђ ─љр║ИP- NG├Ћ Rр╗ўNG",
        "Description": "3 PN Рђб Nh├а ng├х, hр║╗m",
        "Price": "16 tр╗и",
        "Price per m┬▓": "457 tr/m┬▓",
        "Space": "35 m┬▓",
        "Location": "Quр║Гn Hai B├а Trк░ng Рђб 3 ng├аy trк░р╗Џc"
    },
    {
        "Title": "B├Аn nh├а Mр╗╣ ─љ├гnh, Nam Tр╗Ф Li├фm. DT 37m2, 4 tр║Дng, 4 ngр╗Д. Gi├А 6.3 tр╗и",
        "Description": "4 PN Рђб Hк░р╗Џng T├бy Nam Рђб Nh├а ng├х, hр║╗m",
        "Price": "16 tр╗и",
        "Price per m┬▓": "457 tr/m┬▓",
        "Space": "35 m┬▓",
        "Location": "Quр║Гn Nam Tр╗Ф Li├фm Рђб 3 ng├аy trк░р╗Џc"
    },
    {
        "Title": "─љр║▓NG Cр║цP-Mр║ХT PHр╗љ ─љ├ђM QUANG TRUNG 90M-8 Tр║дNG-THANG M├ЂY-FULL Nр╗ўI THр║цT",
        "Description": "5 PN Рђб Hк░р╗Џng ─љ├┤ng Рђб Nh├а mр║иt phр╗Љ, mр║иt tiр╗Ђn",
        "Price": "16 tр╗и",
        "Price per m┬▓": "457 tr/m┬▓",
        "Space": "35 m┬▓",
        "Location": "Quр║Гn Long Bi├фn Рђб 3 ng├аy trк░р╗Џc"
    },
    {
        "Title": "B├ЂN NH├ђ Tр║гP THр╗ѓ Tр║дNG 1 Mр║ХT NG├Ћ ─љр║дU NGUYр╗ёN TR├ЃI CHр╗ѕ 4,5 Tр╗Х",
        "Description": "2 PN Рђб Hк░р╗Џng ─љ├┤ng Рђб Tр║Гp thр╗Ѓ, cк░ x├А",
        "Price": "16 tр╗и",
        "Price per m┬▓": "457 tr/m┬▓",
        "Space": "35 m┬▓",
        "Location": "Quр║Гn Thanh Xu├бn Рђб 3 ng├аy trк░р╗Џc"
    },
    {
        "Title": "L├┤ g├│c ─љ├ф La Th├аnh ,10m ra phр╗Љ, ├┤ t├┤ ─Љр╗Ќ cр╗Гa, KD, nh├а tho├Аng 30m*3T,",
        "Description": "3 PN Рђб Nh├а ng├х, hр║╗m",
        "Price": "16 tр╗и",
        "Price per m┬▓": "457 tr/m┬▓",
        "Space": "35 m┬▓",
        "Location": "Quр║Гn ─љр╗Љng ─љa Рђб 3 ng├аy trк░р╗Џc"
    },
    {
        "Title": "HIр║ЙM!NH├ђ THр║аCH B├ђN-56M2-6 Tр║дNG-THANG M├ЂY-GARA ├ћ T├ћ-KINH DOANH NG├ђY ─љ├іM",
        "Description": "4 PN Рђб Hк░р╗Џng ─љ├┤ng Bр║»c Рђб Nh├а mр║иt phр╗Љ, mр║иt tiр╗Ђn",
        "Price": "16 tр╗и",
        "Price per m┬▓": "457 tr/m┬▓",
        "Space": "35 m┬▓",
        "Location": "Quр║Гn Long Bi├фn Рђб 3 ng├аy trк░р╗Џc"
    },
    {
        "Title": "HIр║ЙM-NH├ђ NGр╗їC THUр╗┤-7 Tр║дNG 115M, THANG M├ЂY, GARA ├ћ T├ћ, Nр╗ўI THр║цT CAO Cр║цP",
        "Description": "5 PN Рђб Nh├а ng├х, hр║╗m",
        "Price": "16 tр╗и",
        "Price per m┬▓": "457 tr/m┬▓",
        "Space": "35 m┬▓",
        "Location": "Quр║Гn Long Bi├фn Рђб 3 ng├аy trк░р╗Џc"
    },
    {
        "Title": "(Sр╗ћ VU├ћNG)mр║иt ng├х ch├╣a L├Аng 50mx4T MT 4.6m 10 tр╗и KD р╗Ъ suр╗Љng oto ─Љр╗Ќ ─љ─љ",
        "Description": "4 PN Рђб Nh├а ng├х, hр║╗m",
        "Price": "16 tр╗и",
        "Price per m┬▓": "457 tr/m┬▓",
        "Space": "35 m┬▓",
        "Location": "Quр║Гn ─љр╗Љng ─љa Рђб 3 ng├аy trк░р╗Џc"
    },
    {
        "Title": "HIр║ЙM! NGр╗їC L├ѓM-KINH DOANH-├ћ T├ћ TR├ЂNH-TH├ћNG-60M-5 Tр║дNG-2 THO├ЂNG-Gр║дN PHр╗љ",
        "Description": "4 PN Рђб Hк░р╗Џng T├бy Nam Рђб Nh├а ng├х, hр║╗m",
        "Price": "16 tр╗и",
        "Price per m┬▓": "457 tr/m┬▓",
        "Space": "35 m┬▓",
        "Location": "Quр║Гn Long Bi├фn Рђб 3 ng├аy trк░р╗Џc"
    },
    {
        "Title": "Cр╗░C HIр║ЙM! C─ѓN G├ЊC 48M-6 Tр║дNG-THANG M├ЂY-GARA ├ћ T├ћ-Gр║дN AEON,CHр╗ѕ HкаN 12Tр╗Х",
        "Description": "4 PN Рђб Hк░р╗Џng ─љ├┤ng Рђб Nh├а ng├х, hр║╗m",
        "Price": "16 tр╗и",
        "Price per m┬▓": "457 tr/m┬▓",
        "Space": "35 m┬▓",
        "Location": "Quр║Гn Long Bi├фn Рђб 3 ng├аy trк░р╗Џc"
    },
    {
        "Title": "THр║гT 100%-B├ЂN NH├ђ PH├џC Lр╗бI-48M-4 NGр╗д-Nр╗ъ Hр║гU-├ћ T├ћ ─љр╗ќ Gр║дN-Sр╗љC HкаN 5 Tр╗Х",
        "Description": "4 PN Рђб Nh├а ng├х, hр║╗m",
        "Price": "16 tр╗и",
        "Price per m┬▓": "457 tr/m┬▓",
        "Space": "35 m┬▓",
        "Location": "Quр║Гn Long Bi├фn Рђб 3 ng├аy trк░р╗Џc"
    },
    {
        "Title": "HIр║ЙM-NHр╗ѕNH 6 Tр╗Х-NH├ђ RI├іNG-33M-3 NGр╗д-Gр║дN AEON-Cр║дU V─еNH TUY SANG PHр╗љ Cр╗ћ",
        "Description": "3 PN Рђб Hк░р╗Џng ─љ├┤ng Bр║»c Рђб Nh├а ng├х, hр║╗m",
        "Price": "16 tр╗и",
        "Price per m┬▓": "457 tr/m┬▓",
        "Space": "35 m┬▓",
        "Location": "Quр║Гn Long Bi├фn Рђб 3 ng├аy trк░р╗Џc"
    },
    {
        "Title": "VIP! SI├іU PHр║еM 60M2-7 Tр║дNG-THANG M├ЂY-FULL Nр╗ўI THр║цT-THр║аCH B├ђN-Gр║дN AEON",
        "Description": "5 PN Рђб Nh├а mр║иt phр╗Љ, mр║иt tiр╗Ђn",
        "Price": "16 tр╗и",
        "Price per m┬▓": "457 tr/m┬▓",
        "Space": "35 m┬▓",
        "Location": "Quр║Гn Long Bi├фn Рђб 3 ng├аy trк░р╗Џc"
    },
    {
        "Title": "HIр║ЙM! KHU VIP PH├ѓN L├ћ-Vр╗ѕA H├ѕ-├ћ T├ћ TR├ЂNH-96M-VIр╗єT Hк»NG-LONG BI├іN-30 Tр╗Х",
        "Description": "4 PN Рђб Nh├а biр╗Єt thр╗▒",
        "Price": "16 tр╗и",
        "Price per m┬▓": "457 tr/m┬▓",
        "Space": "35 m┬▓",
        "Location": "Quр║Гn Long Bi├фn Рђб 3 ng├аy trк░р╗Џc"
    },
    {
        "Title": "Cр╗░C Rр║║-HкаN 12 Tр╗Х- NH├ђ 93M2-5Tр║дNG-THANG M├ЂY-GARA ├ћ T├ћ-6 NGр╗д-KINH DOANH",
        "Description": "6 PN Рђб Hк░р╗Џng T├бy Bр║»c Рђб Nh├а mр║иt phр╗Љ, mр║иt tiр╗Ђn",
        "Price": "16 tр╗и",
        "Price per m┬▓": "457 tr/m┬▓",
        "Space": "35 m┬▓",
        "Location": "Quр║Гn Long Bi├фn Рђб 3 ng├аy trк░р╗Џc"
    }
]